sync_back/__init__.py
sync_back/progress_bar.py
sync_back/random_crap.py
sync_back/term.py
sync_back/utils.py
sync_back-0.2.1.dist-info/entry_points.txt
sync_back-0.2.1.dist-info/WHEEL
sync_back-0.2.1.dist-info/METADATA
sync_back-0.2.1.dist-info/RECORD
