Metadata-Version: 2.1
Name: sync-back
Version: 0.2.1
Summary: 
Author: Deepio
Requires-Python: >=3.10,<4.0
Classifier: Programming Language :: Python :: 3
Classifier: Programming Language :: Python :: 3.10
Requires-Dist: click (>=8.1.3,<9.0.0)
Requires-Dist: rich (>=12.4.4,<13.0.0)
Requires-Dist: toml (>=0.10.2,<0.11.0)
